sphinx_visualised/__init__.py
sphinx_visualised/static/html/link-graph.html
sphinx_visualised/static/html/toctree-graph.html
sphinx_visualised/static/js/convert-tree.js
sphinx_visualised/static/js/link-graph.js
sphinx_visualised/static/js/toctree-graph.js
sphinx_visualised-0.2.3.dist-info/LICENSE
sphinx_visualised-0.2.3.dist-info/METADATA
sphinx_visualised-0.2.3.dist-info/WHEEL
sphinx_visualised-0.2.3.dist-info/top_level.txt
sphinx_visualised-0.2.3.dist-info/RECORD
